{
  "icon": "https://cloudmoon.tos-ap-southeast-1.volces.com/icon_Resident_Evil_4.png",
  "title": "Resident Evil 4",
  "subTitle": "Horror / Action",
  "desc": "生存只是开始。<br><br>浣熊市生物灾难已经过去了六年。<br>作为该事件的幸存者之一，特工里昂·S·肯尼迪被派去营救总统被绑架的女儿。<br>他追踪她到一个偏远的欧洲村庄，那里的村民们出了大问题。<br>而这出大胆营救和艰辛恐怖的故事拉开了帷幕，在这里，生与死、恐怖与宣泄交织在一起。",
  "images": [
    "https://cloudmoon.tos-ap-southeast-1.volces.com/banner_pc_Resident_Evil_4-1.jpg",
    "https://cloudmoon.tos-ap-southeast-1.volces.com/banner_pc_Resident_Evil_4-2.jpg",
    "https://cloudmoon.tos-ap-southeast-1.volces.com/banner_pc_Resident_Evil_4-3.jpg"
  ]
}