{
  "images": [
    "https://play-lh.googleusercontent.com/9-PYw8mwBuIIEWHt3oNDKe0h8Xky6ech8mWl-NbGthX8LvIhuBVdK8ttrBVeLzOjKGI=w526-h296-rw",
    "https://play-lh.googleusercontent.com/iyaRC63b68N3rnUSDJyMa-RaqWhp9Pjkw781AZCj8KIJP_x3OgvybOjolMrIL9cySWP1=w526-h296-rw",
    "https://play-lh.googleusercontent.com/_r6E-IHqwKDqwqNCEdlmthc7pI36yXL5SgWHbx1rYT32sVBIKBlFiuPP11Tgj0I_iTo=w526-h296-rw",
    "https://play-lh.googleusercontent.com/-jNRbZzaVYJPaV9Mx6e1_EJnmoeWlW15ZMJtM-t4zzP_P7t8KdgivxdM0pMBdLPE884=w526-h296-rw",
    "https://play-lh.googleusercontent.com/mmXgRfzKW6JG5kQ42QNxB_UTU5GG9B451sW4qmSI8bSCNu4bzBK7Lgzk5vveVyjrHg=w526-h296-rw"
  ],
  "title": "Seven Knights Idle Adventure",
  "icon": "https://play-lh.googleusercontent.com/rMcSW2bCednEi239X8xFJJ8y_ApvKpYx-ZnWg3SRG6uoq4R77RW2eZTWsKlpsSGk_XI=w240-h480-rw",
  "subTitle": "RPG/Idle RPG",
  "desc": "เรื่องราวอีกหนึ่งบทของเซเว่นไนท์ การปฏิวัติอันแสนสนุกของเหล่าตัวละครใหม่!<br> เรื่องราวการผจญภัยสุดแสนอลหม่านที่มาพร้อมกับตัวเอกคนใหม่ และเหล่าอัศวินเซเว่นไนท์!<br> <br> ▶ เซเว่นไนท์ในแบบฉบับเฉพาะตัวที่แม้จะปล่อยทิ้งไว้ก็สามารถพัฒนาได้<br> ง่ายและรวดเร็วทั้งการต่อสู้และการพัฒนา!<br> ต่อสู้ได้ง่ายๆ ด้วยการล่าแบบอัตโนมัติ และสามารถรับ EXP และทองได้โดยไม่ต้องเชื่อมต่อเกม<br> <br> ▶ ฟอร์มทีมอัศวินที่ไม่เหมือนใคร<br> การปรากฏตัวของเซเว่นไนท์สุดน่ารักและมีเสน่ห์<br> ฟอร์มทีมที่ไม่เหมือนใครด้วยอัศวินที่มีเอกลักษณ์เฉพาะตัว<br> <br> ▶ การต่อสู้เชิงกลยุทธ์ 10 vs 10!<br> การต่อสู้สุดอลังการที่รองรับอัศวินได้สูงสุด 10 คน<br> โชว์เหล่าอัศวินพราวเสน่ห์ที่ไม่เหมือนใครในฟิลด์ ดันเจี้ยน และอารีน่า<br> <br> ▶ เพิ่มความอลังการมากยิ่งขึ้นด้วยคอสตูม และสัตว์เลี้ยง!<br> สร้างอัศวินที่ไม่เหมือนใครด้วยสัตว์เลี้ยงแสนน่ารักและคอสตูมที่มีเอกลักษณ์เฉพาะตัว<br> <br> ▶ กิจกรรมเชื่อมต่อสุดยิ่งใหญ่! แจกรูบี้มากมาย!<br> ซัพพอร์ตการพัฒนาที่รวดเร็ว!<br> พัฒนาเหล่าอัศวินได้อย่างรวดเร็วด้วยรางวัลเชื่อมต่อมากมายที่มอบให้ในทุกๆ วัน <br>========================================================<br>※ แอปพลิเคชั่นนี้มีการจัดเก็บการชำระเงินภายในเกม<br>ฟังก์ชั่นนี้สามารถปิดการใช้งานได้ผ่านการตั้งค่าอุปกรณ์<br>※ ในการดาวน์โหลดเกมนี้ ท่านตกลงยอมรับเงื่อนไขการใช้งานและนโยบายจัดการความเป็นส่วนตัวของเรา<br>- เงื่อนไขการใช้งาน: https://help.netmarble.com/terms/terms_of_service_en<br>- นโยบายจัดการความเป็นส่วนตัว: https://help.netmarble.com/privacy_policy/skiagb"
}