{
  "icon": "https://cloudmoon.tos-ap-southeast-1.volces.com/icon_Human_Fall_Flat.png",
  "title": "Human: Fall Flat",
  "subTitle": "Adventure / Funny",
  "desc": "Human Fall Flat เป็นเกมแพลตฟอร์มฟิสิกส์ที่ตลกขบขันและไร้กังวล ซึ่งตั้งอยู่ในโลกของทิวทัศน์ที่ล่องลอยเหมือนความฝัน<br><br>แต่ละด่านในฝันจะมีสภาพแวดล้อมใหม่ๆ ให้สำรวจ ตั้งแต่คฤหาสน์ ปราสาท และการผจญภัยของชาวแอซเท็ก ไปจนถึงภูเขาหิมะ ทิวทัศน์ยามค่ำคืนที่น่าขนลุก และสถานที่อุตสาหกรรม เส้นทางที่หลากหลายในแต่ละด่านและปริศนาที่สนุกสนานอย่างลงตัวทำให้การสำรวจและความคิดสร้างสรรค์ได้รับรางวัล<br><br>คุณต้องการความช่วยเหลือในการวางหินก้อนนั้นบนหนังสติ๊ก หรือต้องการใครสักคนที่จะทลายกำแพงนั้น?<br><br>ตัวละครของคุณสามารถปรับแต่งได้ ด้วยเสื้อผ้าตั้งแต่ช่างก่อสร้างไปจนถึงเชฟ นักกระโดดร่ม นักขุด นักบินอวกาศ และนินจา เลือกศีรษะ ร่างกายส่วนบนและส่วนล่าง และสร้างสรรค์ด้วยสีสัน!",
  "images": [
    "https://cloudmoon.tos-ap-southeast-1.volces.com/banner_pc_Human_Fall_Flat-1.jpg",
    "https://cloudmoon.tos-ap-southeast-1.volces.com/banner_pc_Human_Fall_Flat-2.jpg",
    "https://cloudmoon.tos-ap-southeast-1.volces.com/banner_pc_Human_Fall_Flat-3.jpg"
  ]
}