{
  "icon": "https://cloudmoon.tos-ap-southeast-1.volces.com/icon_Hades.png",
  "title": "Hades",
  "subTitle": "Action Roguelike / Hack and Slash",
  "desc": "Hades est un jeu d'exploration de donjons de type roguelike divin qui combine les meilleurs aspects des titres acclamés par la critique de Supergiant, y compris l'action rapide de Bastion, l'atmosphère riche et la profondeur de Transistor et la narration axée sur les personnages de Pyre.",
  "images": [
    "https://cloudmoon.tos-ap-southeast-1.volces.com/banner_pc_Hades-1.jpg",
    "https://cloudmoon.tos-ap-southeast-1.volces.com/banner_pc_Hades-2.jpg",
    "https://cloudmoon.tos-ap-southeast-1.volces.com/banner_pc_Hades-3.jpg"
  ]
}