{
  "icon": "https://cloudmoon.tos-ap-southeast-1.volces.com/JoJos_Bizarre_Adventure_All_Star_Battle_R.png",
  "title": "JoJo's Bizarre Adventure: All-Star Battle R",
  "subTitle": "Anime / Action",
  "desc": "Connu pour ses héros charismatiques, son style artistique saisissant et ses phrases inoubliables (« Yare yare daze... »), une autre entrée de JoJo's Bizarre Adventure arrive avec un nouveau coup de poing ! JoJo's Bizarre Adventure: All-Star Battle R !<br><br>• Des visuels époustouflants fidèles au style de Hirohiko Araki<br><br>• 50 personnages jouables de toutes les sagas de JoJo<br><br>• Une variété de modes de jeu",
  "images": [
    "https://cloudmoon.tos-ap-southeast-1.volces.com/banner_pc_JoJos_Bizarre_Adventure_BattleR-1.jpg",
    "https://cloudmoon.tos-ap-southeast-1.volces.com/banner_pc_JoJos_Bizarre_Adventure_BattleR-2.jpg",
    "https://cloudmoon.tos-ap-southeast-1.volces.com/banner_pc_JoJos_Bizarre_Adventure_BattleR-3.jpg"
  ]
}