[
  {
    "id": "com.bluepoch.m.en.reverse1999",
    "title": "Reverse: 1999",
    "image": "https://cloudmoon-1305370474.cos.ap-singapore.myqcloud.com/cloudgame-icon/icon_reverse_1999.webp",
    "status": 1,
    "is_high": false,
    "disabled": false,
    "is_pc": false
  },
  {
    "id": "com.garena.game.haikyu",
    "title": "HAIKYU!! FLY HIGH",
    "image": "https://cloudmoon-1305370474.cos.ap-singapore.myqcloud.com/cloudgame-icon/icon_HAIKYU_FLY_HIGH.webp",
    "status": 1,
    "is_high": false,
    "disabled": false,
    "is_pc": false
  },
  {
    "id": "com.devsisters.ck",
    "title": "CookieRun: Kingdom",
    "image": "https://cloudmoon-1305370474.cos.ap-singapore.myqcloud.com/cloudgame-icon/icon_cookierun_kingdom.webp",
    "status": 1,
    "is_high": false,
    "disabled": false,
    "is_pc": false
  },
  {
    "id": "com.miHoYo.GenshinImpact",
    "title": "Genshin Impact",
    "image": "https://cloudmoon-1305370474.cos.ap-singapore.myqcloud.com/cloudgame-icon/icon_Genshin_Impact.webp",
    "status": 1,
    "is_high": false,
    "disabled": false,
    "is_pc": false
  },
  {
    "id": "com.HoYoverse.hkrpgoversea",
    "title": "Honkai: Star Rail",
    "image": "https://cloudmoon-1305370474.cos.ap-singapore.myqcloud.com/cloudgame-icon/icon_Honkai_Star_Rail.webp",
    "status": 1,
    "is_high": false,
    "disabled": false,
    "is_pc": false
  },
  {
    "id": "com.YoStarEN.Arknights",
    "title": "Arknights",
    "image": "https://cloudmoon-1305370474.cos.ap-singapore.myqcloud.com/cloudgame-icon/icon_Arknights.webp",
    "status": 1,
    "is_high": false,
    "disabled": false,
    "is_pc": false
  },
  {
    "id": "com.kurogame.wutheringwaves.global",
    "title": "Wuthering Waves",
    "image": "https://cloudmoon-1305370474.cos.ap-singapore.myqcloud.com/cloudgame-icon/icon_wuthering_waves.webp",
    "status": 1,
    "is_high": false,
    "disabled": false,
    "is_pc": false
  },
  {
    "id": "com.netmarble.sololv",
    "title": "Solo Leveling:Arise",
    "image": "https://cloudmoon-1305370474.cos.ap-singapore.myqcloud.com/cloudgame-icon/icon_solo_leveling.webp",
    "status": 1,
    "is_high": false,
    "disabled": false,
    "is_pc": false
  },
  {
    "id": "com.aniplex.fategrandorder.en",
    "title": "Fate/Grand Order (En)",
    "image": "https://cloudmoon-1305370474.cos.ap-singapore.myqcloud.com/cloudgame-icon/icon_FGO.webp",
    "status": 1,
    "is_high": false,
    "disabled": false,
    "is_pc": false
  },
  {
    "id": "com.netease.harrypotter.na",
    "title": "Harry Potter: Magic Awakened™",
    "image": "https://cloudmoon-1305370474.cos.ap-singapore.myqcloud.com/cloudgame-icon/icon_Harry_Potter_Magic_Awakened.webp",
    "status": 1,
    "is_high": false,
    "disabled": false,
    "is_pc": false
  },
  {
    "id": "com.HoYoverse.Nap",
    "title": "Zenless Zone Zero",
    "image": "https://cloudmoon-1305370474.cos.ap-singapore.myqcloud.com/cloudgame-icon/icon_zenless_zone_zero_new.webp",
    "status": 1,
    "is_high": false,
    "disabled": false,
    "is_pc": false
  },
  {
    "id": "com.h73.jhqyna",
    "title": "Once Human",
    "image": "https://cloudmoon-1305370474.cos.ap-singapore.myqcloud.com/cloudgame-icon/icon_Once_Human.webp",
    "status": 1,
    "is_high": false,
    "disabled": false,
    "is_pc": false
  },
  {
    "id": "com.kakaogames.gdts",
    "title": "Guardian Tales",
    "image": "https://cloudmoon-1305370474.cos.ap-singapore.myqcloud.com/cloudgame-icon/icon_Guardian_Tales.webp",
    "status": 1,
    "is_high": false,
    "disabled": false,
    "is_pc": false
  },
  {
    "id": "com.netease.dfjssea",
    "title": "Racing Master",
    "image": "https://cloudmoon-1305370474.cos.ap-singapore.myqcloud.com/cloudgame-icon/Racing_Master.webp",
    "status": 1,
    "is_high": false,
    "disabled": false,
    "is_pc": false
  },
  {
    "id": "com.roblox.client",
    "title": "Roblox",
    "image": "https://cloudmoon-1305370474.cos.ap-singapore.myqcloud.com/cloudgame-icon/icon_Roblox.webp",
    "status": 1,
    "is_high": false,
    "disabled": false,
    "is_pc": false
  },
  {
    "id": "com.papegames.lysk.en",
    "title": "Love and Deepspace",
    "image": "https://cloudmoon-1305370474.cos.ap-singapore.myqcloud.com/cloudgame-icon/icon_Love_and_Deepspace.webp",
    "status": 1,
    "is_high": false,
    "disabled": false,
    "is_pc": false
  }
]