{
  "icon": "https://cloudmoon.tos-ap-southeast-1.volces.com/icon_DRAGONZ.png",
  "title": "DRAGON BALL FighterZ",
  "subTitle": "Fighting / Anime",
  "desc": "DRAGON BALL FighterZ рождается из того, что делает серию DRAGON BALL такой любимой и знаменитой: бесконечных захватывающих боев с ее всемогущими бойцами.<br><br>В партнерстве с Arc System Works, DRAGON BALL FighterZ максимизирует высококачественную аниме-графику и обеспечивает легкий для освоения, но сложный для мастерства боевой геймплей.",
  "images": [
    "https://cloudmoon.tos-ap-southeast-1.volces.com/banner_pc_DRAGON_BALL_FighterZ-1.jpg",
    "https://cloudmoon.tos-ap-southeast-1.volces.com/banner_pc_DRAGON_BALL_FighterZ-2.jpg",
    "https://cloudmoon.tos-ap-southeast-1.volces.com/banner_pc_DRAGON_BALL_FighterZ-3.jpg"
  ]
}